botty/__init__.py
botty/bot.py
botty/broadcast.py
botty/buttons.py
botty/config.py
botty/context.py
botty/deps.py
botty/dispatcher.py
botty/env.py
botty/errors.py
botty/filters.py
botty/helpers.py
botty/html.py
botty/keyboards.py
botty/loader.py
botty/middlewares/__init__.py
botty/middlewares/_conversation.py
botty/middlewares/_membership.py
botty/middlewares/misc.py
botty/middlewares/throttling.py
botty/r.py
aiogram_ext-0.10.0.dist-info/WHEEL
aiogram_ext-0.10.0.dist-info/METADATA
aiogram_ext-0.10.0.dist-info/RECORD
